AstroSubtractor/__init__.py
AstroSubtractor/cnn_model.py
AstroSubtractor/data_augmentation.py
AstroSubtractor/data_processing.py
AstroSubtractor/optimization.py
AstroSubtractor-0.1.dist-info/LICENSE.txt
AstroSubtractor-0.1.dist-info/METADATA
AstroSubtractor-0.1.dist-info/WHEEL
AstroSubtractor-0.1.dist-info/top_level.txt
AstroSubtractor-0.1.dist-info/RECORD
